kubios/__init__.py
kubios/kubios.py
kubios-0.1.dist-info/LICENSE.txt
kubios-0.1.dist-info/METADATA
kubios-0.1.dist-info/WHEEL
kubios-0.1.dist-info/top_level.txt
kubios-0.1.dist-info/RECORD
