Metadata-Version: 2.1
Name: kubios
Version: 0.1
Summary: Python package to support KUBIOS file management.
Home-page: https://github.com/PGomes92/kubios
Author: Pedro Gomes
Author-email: pgomes92@gmail.com
License: UNKNOWN
Platform: UNKNOWN
Classifier: Programming Language :: Python :: 2.7
Classifier: License :: OSI Approved :: MIT License
Classifier: Operating System :: OS Independent
